visideas/__init__.py
visideas/visideas.py
visideas-0.0.1.dist-info/METADATA
visideas-0.0.1.dist-info/WHEEL
visideas-0.0.1.dist-info/entry_points.txt
visideas-0.0.1.dist-info/licenses/LICENSE
visideas-0.0.1.dist-info/RECORD
