Metadata-Version: 2.1
Name: visideas
Version: 0.0.1
Summary: A set of tools to help you visualize your ideation list.
Project-URL: Homepage, https://github.com/4gatepylon/VisIdeation
Project-URL: Bug Tracker, https://github.com/4gatepylon/VisIdeation
Author-email: Adriano Hernandez <adrianohernandez2000@gmail.com>
License-File: LICENSE
Classifier: License :: OSI Approved :: GNU General Public License v3 or later (GPLv3+)
Classifier: Operating System :: OS Independent
Classifier: Programming Language :: Python :: 3
Requires-Python: >=3.8
Requires-Dist: click<9,>=8.0.4
Requires-Dist: tabulate>=0.8.10
